bibman/__init__.py
bibman/att_col.py
bibman/base.py
bibman/bib_collection_default.bib
bibman/collection_tree_default.txt
bibman/config.py
bibman/config.yml
bibman/definitions.py
bibman/definitions_.py
bibman/feature.md
bibman/main.py
bibman/onetime_ordering.py
bibman/paper_col.py
bibman/readme.md
bibman/requirement.txt
bibman/sync_code.sh
bibman/talk.txt
bibman/test_bib.py
bibman/this-is-a-pdf.txt
bibman/todo.txt
bibman/tree_list.py
bibman/data/bib_collection.bib
bibman/data/bib_collection.bib.bk
bibman/data/collection_tree.txt
bibman/data/strang2020linear_note
bibman/screenshot/demo1.png
bibman/utils/__init__.py
bibman/utils/data_manager.py
bibman/utils/get_data_from_zotera.py
bibman/utils/network_utils.py
bibman/utils/others.py
bibman-0.3.dist-info/METADATA
bibman-0.3.dist-info/WHEEL
bibman-0.3.dist-info/entry_points.txt
bibman-0.3.dist-info/licenses/LICENSE
bibman-0.3.dist-info/RECORD
