Metadata-Version: 2.1
Name: bibman
Version: 0.3
Summary: A TUI app to manage bibliography
Project-URL: Homepage, https://github.com/ductri/bibman
Project-URL: Bug Tracker, https://github.com/ductri/bibman/issues
Author-email: Tri Nguyen <ductricse@gmail.com>
License-File: LICENSE
Classifier: License :: OSI Approved :: MIT License
Classifier: Operating System :: OS Independent
Classifier: Programming Language :: Python :: 3
Requires-Python: >=3.6
Requires-Dist: anytree==2.8.0
Requires-Dist: bibtexparser==1.4.0
Requires-Dist: pdf2bib==1.0.3
Requires-Dist: pyyaml==6.0.1
Requires-Dist: tqdm==4.61.1
